 [
    {
        "mime": "jpeg",
        "date": "2024-04-12T21:23:12.624",
        "author_name": "Stream",
        "author_username": "Stream",
        "post_id": "1",
        "author_id": "1",
        "content_image": "https://ichef.bbci.co.uk/news/1024/branded_news/00f1/live/4919ed00-24ae-11ef-a13a-0b8c563da930.jpg",
        "author_image": "https://ichef.bbci.co.uk/news/1024/branded_news/00f1/live/4919ed00-24ae-11ef-a13a-0b8c563da930.jpg",
        "content": "What an extraordinary own goal.\r\nLike so many of the clearest, most stark stories, two pictures do almost all of the talking.\r\nFor days, the leaders' teams for the Conservatives and Labour had been t… [+1032 chars]"
    },
    {
        "mime": "jpeg",
        "date": "2024-04-12T21:23:12.624",
        "author_name": "Stream",
        "author_username": "Stream",
        "post_id": "1",
        "author_id": "1",
        "content_image": "https://ichef.bbci.co.uk/news/1024/branded_news/699e/live/39df08c0-24ea-11ef-af40-35017be5d33b.jpg",
        "author_image": "https://ichef.bbci.co.uk/news/1024/branded_news/699e/live/39df08c0-24ea-11ef-af40-35017be5d33b.jpg",
        "content": "US President Joe Biden has apologised to his counterpart Volodymyr Zelensky for delays in military aid to Ukraine and has pledged $225m (£191m) in support.\r\nThe pair met for talks in Paris, a day aft… [+1297 chars]"
    },
    {
        "mime": "jpeg",
        "date": "2024-04-12T21:23:12.624",
        "author_name": "Stream",
        "author_username": "Stream",
        "post_id": "1",
        "author_id": "1",
        "content_image": "https://ichef.bbci.co.uk/news/1024/branded_news/5f66/live/0f9be250-24cb-11ef-bd0f-b54088afbb94.jpg",
        "author_image": "https://ichef.bbci.co.uk/news/1024/branded_news/5f66/live/0f9be250-24cb-11ef-bd0f-b54088afbb94.jpg",
        "content": "Members of the public began arriving outside the cathedral from early in the morning, bringing camping chairs and picnics.\r\nBy the time of the service, thousands were gathered outside the cathedral a… [+958 chars]"
    },
    {
        "mime": "jpeg",
        "date": "2024-04-12T21:23:12.624",
        "author_name": "Stream",
        "author_username": "Stream",
        "post_id": "1",
        "author_id": "1",
        "content_image": "https://ichef.bbci.co.uk/news/1024/branded_news/824e/live/3f6fb2a0-2416-11ef-894c-a90c371c460d.jpg",
        "author_image": "https://ichef.bbci.co.uk/news/1024/branded_news/824e/live/3f6fb2a0-2416-11ef-894c-a90c371c460d.jpg",
        "content": "Most of the civilians we meet were trained in the CNAs Victoria Base, south of Haimual. Driving on winding, bumpy roads through dense forests and mountainous terrain we arrive at the base.\r\nWe see hu… [+990 chars]"
    },
    {
        "mime": "jpeg",
        "date": "2024-04-12T21:23:12.624",
        "author_name": "Stream",
        "author_username": "Stream",
        "post_id": "1",
        "author_id": "1",
        "content_image": "https://ichef.bbci.co.uk/news/1024/branded_news/bae2/live/675716e0-24c6-11ef-a13a-0b8c563da930.jpg",
        "author_image": "https://ichef.bbci.co.uk/news/1024/branded_news/bae2/live/675716e0-24c6-11ef-a13a-0b8c563da930.jpg",
        "content": "A 71-year-old woman found dead in her home is determined to have been killed by a black bear, in the first known fatal attack by one of the animals in California. \r\nWhen police entered Patrice Miller… [+1722 chars]"
    },
    {
        "mime": "jpeg",
        "date": "2024-04-12T21:23:12.624",
        "author_name": "Stream",
        "author_username": "Stream",
        "post_id": "1",
        "author_id": "1",
        "content_image": "https://ichef.bbci.co.uk/news/1024/branded_news/bd59/live/426a1b90-2492-11ef-a13a-0b8c563da930.png",
        "author_image": "https://ichef.bbci.co.uk/news/1024/branded_news/bd59/live/426a1b90-2492-11ef-a13a-0b8c563da930.png",
        "content": "They were mercilessly criticised when they built fences; but the reality is that what the EU is doing is not working,\" says Giorgio. \"We have no idea who is coming in: people are falling through the … [+1818 chars]"
    },
    {
        "mime": "jpeg",
        "date": "2024-04-12T21:23:12.624",
        "author_name": "Stream",
        "author_username": "Stream",
        "post_id": "1",
        "author_id": "1",
        "content_image": "https://ichef.bbci.co.uk/news/1024/branded_news/6be8/live/0a410910-242c-11ef-80aa-699d54c46324.png",
        "author_image": "https://ichef.bbci.co.uk/news/1024/branded_news/6be8/live/0a410910-242c-11ef-80aa-699d54c46324.png",
        "content": "The search for British broadcaster Michael Mosley has resumed after he went missing while on holiday on the Greek island of Symi.\r\nKnown for his TV programmes and his Just One Thing podcast on BBC Ra… [+2066 chars]"
    },
    {
        "mime": "jpeg",
        "date": "2024-04-12T21:23:12.624",
        "author_name": "Stream",
        "author_username": "Stream",
        "post_id": "1",
        "author_id": "1",
        "content_image": "https://ichef.bbci.co.uk/news/1024/branded_news/cab2/live/d4cfbec0-21b0-11ef-baa7-25d483663b8e.jpg",
        "author_image": "https://ichef.bbci.co.uk/news/1024/branded_news/cab2/live/d4cfbec0-21b0-11ef-baa7-25d483663b8e.jpg",
        "content": "In Lakshanis apartment, a grey curtain is pulled across the barred windows - shutting the room off from the outside world.\r\nWe dont go outside. Were always scared, the 23-year-old told us when we vis… [+1560 chars]"
    },
    {
        "mime": "jpeg",
        "date": "2024-04-12T21:23:12.624",
        "author_name": "Stream",
        "author_username": "Stream",
        "post_id": "1",
        "author_id": "1",
        "content_image": "https://ichef.bbci.co.uk/news/1024/branded_news/be74/live/ea0ada40-2453-11ef-baa7-25d483663b8e.png",
        "author_image": "https://ichef.bbci.co.uk/news/1024/branded_news/be74/live/ea0ada40-2453-11ef-baa7-25d483663b8e.png",
        "content": "A woman who allegedly inspired the character Martha in the hit Netflix drama Baby Reindeer is suing the streamer for defamation, negligence and privacy violations.\r\nFiona Harvey, a UK lawyer who says… [+2262 chars]"
    },
    {
        "mime": "jpeg",
        "date": "2024-04-12T21:23:12.624",
        "author_name": "Stream",
        "author_username": "Stream",
        "post_id": "1",
        "author_id": "1",
        "content_image": "https://ichef.bbci.co.uk/news/1024/branded_news/be30/live/b5ef5830-23d6-11ef-875c-47a7ad92adab.jpg",
        "author_image": "https://ichef.bbci.co.uk/news/1024/branded_news/be30/live/b5ef5830-23d6-11ef-875c-47a7ad92adab.jpg",
        "content": "The park later posted on behalf of the waterfall saying, \"I didn't expect to meet everyone this way\".\r\n\"As a seasonal scenery I can't guarantee that I will be in my most beautiful form everytime you … [+1380 chars]"
    },
    {
        "likes": false,
        "likes_counter": 0,
        "date": "2024-04-25T16:50:47.005",
        "post_id": "2f7308aa-517f-4647-8e59-ad5494c8cbcc",
        "author_id": "s1rsJ0aqVNNy90Pp13S6EWCkyTh1",
        "author_name": "Aminu Abdulfattah ",
        "author_username": "Abdulfattah ",
        "author_image": "https://firebasestorage.googleapis.com/v0/b/stream-6fa32.appspot.com/o/USER%2FIMAGES%2Fs1rsJ0aqVNNy90Pp13S6EWCkyTh1%2F1d4f073f-26c3-44ef-b677-3396518b4b8e?alt=media&token=6456ba0b-ddb1-4c88-9204-3f955059f71d",
        "content_image": "https://ichef.bbci.co.uk/news/1024/branded_news/1801C/production/_133223389_34b56c59d4021e582dcfd8187436834126a00bb0.jpg",
        "content": "Media caption, Watch: Cavalry horses cause chaos in London\r\nFour people have been taken to hospital after five runaway horses of the Household Cavalry threw off their riders and raced through London.… [+5248 chars]"
    },
    {
        "likes": false,
        "likes_counter": 0,
        "date": "2024-04-25T16:50:29.551",
        "post_id": "569fa2f7-9a9d-4e2b-ada2-8f8b4b7be9c4",
        "author_id": "s1rsJ0aqVNNy90Pp13S6EWCkyTh1",
        "author_name": "Aminu Abdulfattah ",
        "author_username": "Abdulfattah ",
        "author_image": "https://firebasestorage.googleapis.com/v0/b/stream-6fa32.appspot.com/o/USER%2FIMAGES%2Fs1rsJ0aqVNNy90Pp13S6EWCkyTh1%2F1d4f073f-26c3-44ef-b677-3396518b4b8e?alt=media&token=6456ba0b-ddb1-4c88-9204-3f955059f71d",
        "content_image": "https://ichef.bbci.co.uk/news/1024/branded_news/FEE8/production/_128365256_weapons_promo_v2.png",
        "content": "A $61bn package of military aid for Ukraine has been passed by the US Senate and is headed to President Joe Biden's desk to be signed into law. So what weapons might Ukraine receive and what differen… [+3702 chars]"
    },
    {
        "likes": false,
        "likes_counter": 0,
        "date": "2024-05-01T13:46:34.336",
        "post_id": "81f87638-e49d-4a76-881d-cc73aa573f71",
        "author_id": "s1rsJ0aqVNNy90Pp13S6EWCkyTh1",
        "author_name": "Aminu Abdulfattah ",
        "author_username": "Abdulfattah ",
        "author_image": "https://firebasestorage.googleapis.com/v0/b/stream-6fa32.appspot.com/o/USER%2FIMAGES%2Fs1rsJ0aqVNNy90Pp13S6EWCkyTh1%2F1d4f073f-26c3-44ef-b677-3396518b4b8e?alt=media&token=6456ba0b-ddb1-4c88-9204-3f955059f71d",
        "content_image": null,
        "content": "Privacy is the key 🎧"
    },
    {
        "likes": false,
        "likes_counter": 0,
        "date": "2024-04-25T17:14:36.117",
        "post_id": "ab18397e-840d-49f9-9bd8-7cf10a12624d",
        "author_id": "s1rsJ0aqVNNy90Pp13S6EWCkyTh1",
        "author_name": "Aminu Abdulfattah ",
        "author_username": "Abdulfattah ",
        "author_image": "https://firebasestorage.googleapis.com/v0/b/stream-6fa32.appspot.com/o/USER%2FIMAGES%2Fs1rsJ0aqVNNy90Pp13S6EWCkyTh1%2F1d4f073f-26c3-44ef-b677-3396518b4b8e?alt=media&token=6456ba0b-ddb1-4c88-9204-3f955059f71d",
        "content_image": "https://ichef.bbci.co.uk/news/1024/branded_news/BC3F/production/_133219184_klimtafp.jpg",
        "content": "A painting by the Austrian artist Gustav Klimt that was believed lost for the past 100 years, is to be auctioned in Vienna. \r\nThere are many unanswered questions about the unfinished painting, Portra… [+2513 chars]"
    }
]